[
  {
    "NIK": "1234567890123456",
    "nama": "Ahmad Subarjo",
    "jenis_kelamin": "Laki-laki",
    "tempat_tanggal_lahir": "Surabaya, 10 Januari 2005",
    "alamat": "Jl. Mawar No. 10, Surabaya",
    "nama_ayah": "Bapak Budi",
    "nama_ibu": "Ibu Siti",
    "nomor_hp": "081234567890"
  },
  {
    "NIK": "6543210987654321",
    "nama": "Siti Aminah",
    "jenis_kelamin": "Perempuan",
    "tempat_tanggal_lahir": "Malang, 20 Februari 2006",
    "alamat": "Jl. Melati No. 5, Malang",
    "nama_ayah": "Bapak Joko",
    "nama_ibu": "Ibu Ani",
    "nomor_hp": "087654321098"
  }
  // Tambahkan data santri lainnya di sini
]
